odoo/addons/stock_available_to_promise_release_dynamic_routing/README.rst
odoo/addons/stock_available_to_promise_release_dynamic_routing/__init__.py
odoo/addons/stock_available_to_promise_release_dynamic_routing/__manifest__.py
odoo/addons/stock_available_to_promise_release_dynamic_routing/i18n/stock_available_to_promise_release_dynamic_routing.pot
odoo/addons/stock_available_to_promise_release_dynamic_routing/readme/CONTRIBUTORS.rst
odoo/addons/stock_available_to_promise_release_dynamic_routing/readme/DESCRIPTION.rst
odoo/addons/stock_available_to_promise_release_dynamic_routing/static/description/icon.png
odoo/addons/stock_available_to_promise_release_dynamic_routing/static/description/index.html
odoo/addons/stock_available_to_promise_release_dynamic_routing/tests/__init__.py
odoo/addons/stock_available_to_promise_release_dynamic_routing/tests/test_release_dynamic_routing.py
odoo13_addon_stock_available_to_promise_release_dynamic_routing-13.0.1.0.1.dist-info/METADATA
odoo13_addon_stock_available_to_promise_release_dynamic_routing-13.0.1.0.1.dist-info/WHEEL
odoo13_addon_stock_available_to_promise_release_dynamic_routing-13.0.1.0.1.dist-info/top_level.txt
odoo13_addon_stock_available_to_promise_release_dynamic_routing-13.0.1.0.1.dist-info/RECORD
