Metadata-Version: 2.1
Name: odoo13-addon-stock-available-to-promise-release-dynamic-routing
Version: 13.0.1.0.1
Summary: Glue between moves release and dynamic routing
Home-page: https://github.com/OCA/wms
Author: Camptocamp, Odoo Community Association (OCA)
Author-email: support@odoo-community.org
License: AGPL-3
Platform: UNKNOWN
Classifier: Programming Language :: Python
Classifier: Framework :: Odoo
Classifier: License :: OSI Approved :: GNU Affero General Public License v3
Classifier: Development Status :: 3 - Alpha
Requires-Python: >=3.5
Requires-Dist: odoo13-addon-stock-available-to-promise-release
Requires-Dist: odoo13-addon-stock-dynamic-routing
Requires-Dist: odoo (<13.1dev,>=13.0a)
